{
  "project_info": {
    "project_number": "668572969426",
    "firebase_url": "https://fragmentos-d22de.firebaseio.com",
    "project_id": "fragmentos-d22de",
    "storage_bucket": "fragmentos-d22de.appspot.com"
  },
  "client": [
    {
      "client_info": {
        "mobilesdk_app_id": "1:668572969426:android:3c45efaa01c7c89b1b000b",
        "android_client_info": {
          "package_name": "com.sixst06.fragmentos"
        }
      },
      "oauth_client": [
        {
          "client_id": "668572969426-eumsib6j5f0ethcp22gtpqqvd37acvh7.apps.googleusercontent.com",
          "client_type": 3
        }
      ],
      "api_key": [
        {
          "current_key": "AIzaSyAn9cbwuWOb1VR1jN06znD2c0o0qW15TjY"
        }
      ],
      "services": {
        "appinvite_service": {
          "other_platform_oauth_client": [
            {
              "client_id": "668572969426-eumsib6j5f0ethcp22gtpqqvd37acvh7.apps.googleusercontent.com",
              "client_type": 3
            }
          ]
        }
      }
    }
  ],
  "configuration_version": "1"
}